{
  "family_enable": true,
  "family": "After Effects",
  "vendor": "Adobe",
  "abbreviation": "AFX",
  "releases": [
    {
      "release_number": "CS6",
      "release_extension": ".aep",
      "project_template": "null_adobe_aftereffects_CS6.aep",
      "project_workspace": null,
      "project_directories": [],
      "default_outputs": [],
      "architecture_fallback": true,
      "platforms": [
        {
          "windows": {
            "executable_x32": null,
            "flags_x32": [],
            "executable_x64": null,
            "flags_x64": []
          }
        },
        {
          "darwin": {
            "executable_x32": null,
            "flags_x32": [],
            "executable_x64": "/Applications/Adobe After Effects CS6/Adobe After Effects CS6.app/Contents/MacOS/After Effects",
            "flags_x64": []
          }
        },
        {
          "linux": {
            "executable_x32": null,
            "flags_x32": [],
            "executable_x64": null,
            "flags_x64": []
          }
        }
      ]
    }
  ]
}